vsutillib/mkv/__init__.py
vsutillib/mkv/mkvutils.py
vsutillib/mkv/classes/__init__.py
vsutillib/mkv/classes/mkvattachments.py
vsutillib/mkv/classes/mkvclassutil.py
vsutillib/mkv/classes/mkvcommand.py
vsutillib/mkv/classes/mkvcommandparser.py
vsutillib/mkv/classes/verifycommand.py
vsutillib/mkv/classes/verifystructure.py
vsutillib_mkv-1.6.2.dist-info/AUTHORS
vsutillib_mkv-1.6.2.dist-info/LICENSE.txt
vsutillib_mkv-1.6.2.dist-info/METADATA
vsutillib_mkv-1.6.2.dist-info/WHEEL
vsutillib_mkv-1.6.2.dist-info/top_level.txt
vsutillib_mkv-1.6.2.dist-info/RECORD
