Metadata-Version: 2.1
Name: vsutillib-mkv
Version: 1.6.2
Summary: vsutillib.mkv sub package part of vsutillib
Home-page: https://pypi.org/project/vsutillib-mkv/
Author: Efrain Vergara
Author-email: akai10tsuki@gmail.com
License: MIT
Platform: UNKNOWN
Requires-Python: >=3.8.1, <3.9
Requires-Dist: natsort (>=7.0.1)
Requires-Dist: vsutillib-files (>=1.6.3)
Requires-Dist: vsutillib-media (>=1.6.2)
Requires-Dist: vsutillib-misc (>=1.6.0)
Requires-Dist: vsutillib-process (>=1.6.0)
